vibemem/__init__.py
vibemem/api.py
vibemem/cli.py
vibemem/config.py
vibemem/embeddings.py
vibemem/models.py
vibemem/py.typed
vibemem/scope.py
vibemem/util.py
vibemem/store/__init__.py
vibemem/store/base.py
vibemem/store/chroma_cache.py
vibemem/store/weaviate_store.py
vibemem-0.2.7.dist-info/METADATA
vibemem-0.2.7.dist-info/WHEEL
vibemem-0.2.7.dist-info/entry_points.txt
vibemem-0.2.7.dist-info/licenses/LICENSE
vibemem-0.2.7.dist-info/RECORD
