Metadata-Version: 2.4
Name: vibemem
Version: 0.2.7
Summary: Memory management tool for vibe-coding agents using Weaviate and optional Chroma cache
Author: VibeMem
License:                     GNU GENERAL PUBLIC LICENSE
License-File: LICENSE
Keywords: agents,chromadb,cli,memory,rag,weaviate
Classifier: Development Status :: 3 - Alpha
Classifier: Environment :: Console
Classifier: Intended Audience :: Developers
Classifier: License :: OSI Approved :: GNU General Public License v3 (GPLv3)
Classifier: Programming Language :: Python :: 3
Classifier: Programming Language :: Python :: 3.10
Classifier: Programming Language :: Python :: 3.11
Classifier: Programming Language :: Python :: 3.12
Classifier: Typing :: Typed
Requires-Python: >=3.10
Requires-Dist: pydantic>=2.6.0
Requires-Dist: rich>=13.7.0
Requires-Dist: typer>=0.12.0
Requires-Dist: weaviate-client>=4.0.0
Provides-Extra: cache
Requires-Dist: chromadb>=0.5.0; extra == 'cache'
Provides-Extra: dev
Requires-Dist: mypy>=1.8.0; extra == 'dev'
Requires-Dist: pytest-mock>=3.12.0; extra == 'dev'
Requires-Dist: pytest>=7.4.0; extra == 'dev'
Requires-Dist: ruff>=0.5.0; extra == 'dev'
